{
  "source_url": "https://medoxhospital.com/",
  "title": "Best Chest Specialists in Lucknow | DR.Y.N.CHAUBEY",
  "heading": "Welcome to Medox Hospital",
  "description": "Dr Y N Chaubey is one of the Best Chest Specilist Doctor in Lucknow. Contact to Medox Hospital for Best Chest Physicians in Lucknow and Pulmonologist Doctors in Lucknow.We provide Asthma Allergy treatment,Lungs specialist,Chest Surgeory in Lucknow also provide a Lungs related problems.",
  "emails": [
    "info@medoxhospital.com"
  ],
  "phones": [
    "+91 522 401 0303"
  ],
  "addresses": [],
  "text": "Best Chest Specialists in Lucknow | DR.Y.N.CHAUBEY × Scan QR Code to Make Payment Close Email info@medoxhospital.com Contact Us +91 522 401 0303 Home About Us Background Vision & Mission Our facilities Administrative Message Services Departments Gallery OPD ICU Programs & Celebrations Career Contact Us Contact Map Staff Directory Make A Payment Appointment Now QUALITY CARE Your Health is our priority APPOINTMENT Family Care Affordable solutions SERVICES PROPER CHECKUP Your Health is our priority CONTACT US Welcome to Medox Hospital We've built a long standing relationship based on trust Personalized patient care is what sets Medox Hospital apart. When you visit our Hospital you can expect to receive world class care. Expert Chest Physician Specialist and caring clinical staff provide you with an exceptional health care experience. Personalized patient care is what sets Medox Hospital apart. We are well-known for providing fast and effective treatment service of diseases affecting the Lungs, Chest and Respiratory System. Our Pulmonologist Doctors focus on the Respiratory Chronic Diseases like Pneumonia, Asthma, Lung Cancer, Thoracic Surgery, Tuberculosis, Breathlessness, Chronic Bronchitis (COPD), Pulmonology Diseases, Complicated Chest Infections, and other diseases related Lungs and Pulmonology Cases. We have specialized Hospital, with world-class facilities, which also focus on all type of infections, allergic and chronic ailment with a panel of qualified Experienced Doctors, nursing, and staff in Lucknow. Contact  to Best Thoracic Chest Surgeons in Lucknow Dr Y N Chaubey MBBS, DNB, (Pulmonary Medicine), FCCP (USA) Foromely at JIMPMER Pondicherry & fortis Delhi fellow American College of chest Physician (USA) Dr Y N Chaubey is having vast experience in treating complicated respiratory diseases, tuberculosis Interstitial lung diseases pleural diseases and sleep disorders, Doing Diagnostic and therapeutic, Bronchoscopy, Biopsies, Pleurodesis & other pleural interventions and sleep studies. He has also completed \"National course on educational science for health professinal\"  of national teacher's training center, ministry of health govt of India. He was coguide for post graduate research projects related to Interstitial preumonitis & DLCO in COPD. With extensive experience, Dr Y N Chaubey is the most trustworthy and recognized doctor in Pulmonology field. He has established “Medox Hospital in Lucknow” which is the advanced respiratory set-up in Lucknow. Dr Y N Chaubey has a huge experience in handling all types of complicated respiratory ailments along with other chest related procedures with high success rate. Always Preferred experienced doctor for treatment related to all kinds of chest diseases, lung diseases, and respiratory diseases.\nDr Y N Chaubey aims to provide the best of medical treatment and care to all his patients. Dr Y N Chaubey is One of the Best Chest Specialist Doctor in Lucknow. Contact Medox Hospital for Best Chest Physician in Lucknow and Pulmonologist in Lucknow .We provide Best Asthma Allergy treatment,Lungs Specialist, Chest Physician & Chest Surgeory in Lucknow , and also provide a Asthma Treatment and Lungs related problems. We Serve Better Than Any Other! The Best Medical Care Services in Lucknow City see all services Testi Monials Dr. Y N Chaubey Sir is very humble and kind doctor who is very sincere towards his patient. Abhishek Agrawal Very professional. Explained what the problem was and gave me a clear set of medicines and instructions as to how I should proceed. Does not ask for unnecessary investigations and is very thorough in his approach. Would highly recommend Medox Hospital @Dr. Chaubey Tikanath yadav Visited Dr Chaubey for chronic cough  and breathlesness treatment. He thoroughly examined me and patiently listened to all my complaints. He prescribed me very few tests and post that put me on treatment for asthma and thanks to him today I have no cough or breathlesness. I would recommend Medox Hospital for all types of chest disease treatment. Saurabh Srivastava Akash Singh is now six years post liver transplant and is enjoying her new lease on life she is now the proud grandmother. All this seemed like a distant dream six years ago when she could not care for her children, barely walk nor eat and was worried about her a future she did not think she could be a part of. She and her children feel lucky and would also like to be organ donors as they now recognize the impact this act has on others lives. Manoj Verma Ayush Gupta is now six years post liver transplant and is enjoying her new lease on life she is now the proud grandmother. All this seemed like a distant dream six years ago when she could not care for her children, barely walk nor eat and was worried about her a future she did not think she could be a part of. She and her children feel lucky and would also like to be organ donors as they now recognize the impact this act has on others lives. Ayush Gupta Akash Singh is now six years post liver transplant and is enjoying her new lease on life she is now the proud grandmother. All this seemed like a distant dream six years ago when she could not care for her children, barely walk nor eat and was worried about her a future she did not think she could be a part of. She and her children feel lucky and would also like to be organ donors as they now recognize the impact this act has on others lives. Akash Singh Anjali Tripathi is now six years post liver transplant and is enjoying her new lease on life she is now the proud grandmother. All this seemed like a distant dream six years ago when she could not care for her children, barely walk nor eat and was worried about her a future she did not think she could be a part of. She and her children feel lucky and would also like to be organ donors as they now recognize the impact this act has on others lives. Anjali Tripathi Useful Links Services Chest Specialist in Lucknow Lungs Specialist in Lucknow Asthma Specialist in Lucknow Contact Us CP-2, Near Bhawana Complex, Ring Road, Sector F, Jankipuram, Lucknow. info@medoxhospital.com +91 522 401 0303 © Copyright 2022 - Medox Hospital | All right reserved. Write Your Testimonial",
  "text_truncated": false,
  "extracted_at": "2026-06-16T02:36:17+00:00",
  "facility_id": "04309af6-5084-4273-ba40-df461eb616fd",
  "facility_name": "Medox Hospital",
  "http_status": 200
}