{
  "source_url": "https://srchospitals.com/",
  "title": "SRC – Medical & Maternity Centre | Best Hospital in Delhi",
  "heading": "💬What Our Patients Say About SRC Hospital",
  "description": "Expert maternity, gynecology, pediatric, and family care at SRC – Medical & Maternity Centre. Compassionate doctors, modern facilities & 24/7 emergency support.",
  "emails": [],
  "phones": [
    "+919355118687 8"
  ],
  "addresses": [],
  "text": "SRC – Medical & Maternity Centre | Best Hospital in Delhi Skip to content SRC Hospital Open Button Close Button Home About Us Doctors Dr. Priyanka Gupta – Obstetrician, Gynaecologist and Infertility Specialist Dr. Puneet Aggarwal – Pulmonologist Departments Gynecology & Obstetrics Pediatrics Department Pulmonology Department General Medicine Department Emergency & Trauma Department Specialisation TB Treatment in Delhi – Symptoms, Diagnosis & Care Bronchoscopy diagnostic and therapeutic procedure by pulmonologist Asthma treatment, Causes & Symptoms Infertility Treatment – Causes, Symptoms & Solutions Sleep Study & Sleep Apnoea–Related Disorders Breast Cysts Irregular Menstruation Monopause UTI Symptoms and Treatment in Women | Causes & Prevention Book Appointment Contact Us Blogs Delhi Pollution and Its Impact on Heart Health World Tuberculosis Day (24 March): Why Early TB Detection Can Save Lives Book Appointment Healthcare Take Care of your Health with Us! Our team of experienced doctors and healthcare professionals is dedicated to providing personalized care tailored to your unique needs… For Appointments +919355118687 8 AM - 8PM Our Specialized Doctors Dr. Priyanka Gupta – Obstetrician, Gynaecologist and Infertility Specialist Dr. Puneet Aggarwal – Pulmonologist Read More Book Appointment Our Specialities - Highlights Expert, compassionate care across our key medical departments. postcategory1 Services Why Do You Get a Dry Cough at Night? Common Causes and Treatment Read More UTI Symptoms and Treatment in Women | Causes & Prevention Read More TB Treatment in Delhi – Symptoms, Diagnosis & Care Read More Asthma treatment, Causes & Symptoms Read More Bronchoscopy diagnostic and therapeutic procedure by pulmonologist Read More Infertility Treatment – Causes, Symptoms & Solutions Read More Sleep Study & Sleep Apnoea–Related Disorders Read More 💬What Our Patients Say About SRC Hospital Real experiences. Real care. Real trust. Delivery Patient Gynecology & Obstetrics Excellent Delivery Care ☆ ☆ ☆ ☆ ☆ “My experience at SRC Hospital was excellent. Dr. Priyanka Gupta handled my delivery with great care and confidence. The staff was supportive throughout. I felt completely safe and well cared for.” Pulmonology Patient Respiratory Care Best Respiratory Treatment ☆ ☆ ☆ ☆ ☆ “Thank you Dr. Puneet Aggarwal for your excellent treatment and kind support. The entire team took great care of me during my treatment. I am very satisfied with the services.” Patient Attendant General Services Clean & Well-Managed Hospital ☆ ☆ ☆ ☆ ☆ “My wife was treated at SRC Hospital and the service was outstanding. Doctors explained everything clearly and the hospital cleanliness was excellent. Truly impressed by the overall care.” Mother Patient Maternity Care Safe Pregnancy Experience ☆ ☆ ☆ ☆ ☆ “Dr. Priyanka Gupta guided me with confidence and supported me throughout my pregnancy. I had a safe delivery and received great care from the entire staff.” ⭐ Our Promise to Every Patient 1000+ Happy Patients Expert Doctors With 15+ Years Experience Clean & Safe Hospital Environment 24×7 Supportive Staff See Real Patient Experiences Verified patient feedback collected at SRC Hospital Call Now Book Appointment Find Us Ministry of Health & Family Welfare (India) https://www.mohfw.gov.in National Health Portal (NHP India) https://www.nhp.gov.in Home About Us Blogs FAQ SRC https://srchospitals.com/wp-content/uploads/2025/11/SRC.mp4 Meta Log in Follow Us 📞 931155867 📍 SRC Medical and Maternity Centre A-1/2, Mangeram Park, Kanjhawla Road, Opposite Bank of Baroda © 2025 SRC – Medical & Maternity Centre | srchospitals.com | All Rights Reserved. By Themespride",
  "text_truncated": false,
  "extracted_at": "2026-06-16T02:58:21+00:00",
  "facility_id": "37fcd8ff-0d63-4129-9c09-0d4bdb8afa53",
  "facility_name": "SRC Medical and Maternity Centre",
  "http_status": 200
}