{
  "source_url": "https://lifecarediagnostics.com/",
  "title": "Nearest NABL Certified Lab Tests in Mumbai",
  "heading": "Home",
  "description": "Find the closest NABL-accredited lab in Mumbai for your diagnostic tests with Lifecare Diagnostics. Book online today!",
  "emails": [],
  "phones": [
    "9167223838"
  ],
  "addresses": [],
  "text": "Nearest NABL Certified Lab Tests in Mumbai Skip to content NABL Accredited Laboratory Helpline: 9167223838 Sign in Upload Prescription Home About Us Services Advanced Pathology Serology Cytopathology Immunology Biochemistry Endrocrinology Microbiology Clinical Pathology Haematology Histopathology Influenza Panel and H1N1 Special Monsoon Care Digital X-ray 3D/4D Ultrasound with Color Doppler Digital Mammography BMD dexa Cardiac Imaging Computerized Stress Test ECG Dental Imaging Digital OPG Cephalometry IOPA Occlusal View PFT EEG Audiometry Total Body Fat Analysis Advanced Dentistry Speciality Clinics Diabetic Clinic Allergy Clinic Arthritis Clinic Allergy Testing Eye Chekup ENT Cancer Detection HIV Detection and Counselling Consultants Vet Pathology Centres Health Packages Test List Book an appointment Covid19 RT PCR Swab Test Rapid Antigen Test Antibody Test Partner with us Upload Prescription Sign in Home Banner01 Banner03 Banner02 #LiveBetterWithLifecare #LiveBetterWithLifecare #LiveBetterWithLifecare Get our health package based on your age, gender and lifestyle risks Get our health package based on your age, gender and lifestyle risks Get our health package based on your age, gender and lifestyle risks Banner04 Banner05 Banner06 Banner06 Prostate Health Camp For Men Home Care Get test from comfort of your home KNOW MORE Health Packages Better Health With Preventive Healthcare for all Age Groups KNOW MORE Corporate Care Customized programs for your company KNOW MORE COVID19 Get yourself tested for COVID 19 KNOW MORE ABOUT LIFECARE Established in 1995, Lifecare is the country's premier full-service diagnostic center with laboratory, providing expertise in imaging and digital pathology services. Our integrated diagnostic services help doctors personalize patient care to optimally treat disease and maintain health and wellness. We are committed to providing only the highest level of testing quality and service and working with you to provide unique solutions to your most challenging needs. READ MORE HEALTH PACKAGES ALLERGY TESTING ₹13000 ₹12100 Know more ANEMIA SCREENING ₹3810 ₹2850 Know more BASIC CHECK ₹2030 ₹1200 Know more BASIC HEALTH CHECKUP gold: ₹6470 ₹4800 silver: ₹3600 ₹2500 Know more BONE CARE silver: ₹4770 ₹3500 gold: ₹11290 ₹8500 platinum: ₹14040 ₹10500 Know more VIEW ALL DNA Test COMPLETE GENOMICS PACKAGE ₹40000 ₹33000 Know more FITNESS GENOMICS ₹13000 ₹11000 Know more HEALTH GENOMICS ₹26000 ₹22000 Know more NUTRIGENOMICS ₹13000 ₹11000 Know more NUTRITION + FITNESS COMBO PACKAGE ₹19500 ₹16500 Know more VIEW ALL Organs Bones View more Heart View more Kidney View more Liver View more Lungs View more Thyroid View more Lifestyle Risks Allergy View more Anaemia View more Cancer View more Diabetes View more Digestive Conditions View more Fever View more Hormones View more Immunity View more Infertility Check View more Obesity View more For Updates and Health Care tips. Email * OUR SERVICES Advanced Pathology Know More Digital X-ray Know More 3D/4D Ultrasound with Color Doppler Know More Digital Mammography Know More BMD dexa Know More Cardiac Imaging Know More Dental Imaging Know More PFT Know More EEG Know More Audiometry Know More VIEW ALL M+ Patients Served M+ Test Conducted + Test Available + Doctors + Collection Points + Corporate Google Rating : 4.9 TESTIMONIALS Mr Dilip Sen Lion Raju Manvani Customer Testimonial Video-3 Customer Testimonial 15 Customer Testimonial Video-10 Customer Testimonial Video-9 Customer Testimonial Video-8 Customer Testimonial Video-7 Customer Testimonial Video-6 Customer Testimonial Video-4 Customer Testimonial Video 1 Customer Testimonial Video-2 I visited for health check up. The service was really good. Had a great service. This is the best center in the city for all the health check ups. I recommend everyone . Quick reports and it’s a clean premises too. Thank you for providing the service Mannat Noor Amazing service very well organized I was there for few test since from beginning staff is so friendly and helpful was expecting test to take time since it was crowded but to my surprise all test were done so fast Overall very well organized place . Highly recommended Avinash Singh Lifecare Diagnostics provide very well managed and excellent services for all medical diagnostic tests under one roof. Staff was very courteous and helpful. Less wait time for patients and comparatively faster availability of reports on same day than other diagnostic centers, this is what we like the most. Rates are also very reasonable & affordable for a common man. I would definitely recommend Lifecare to my relatives, friends and known persons requiring medical tests. Vivek Powle Amazing service very well organized I was there for few test since from beginning staff is so friendly and helpful was expecting test to take time since it was crowded but to my surprise all test were done so fast Overall very well organized place . Highly recommended Avinash Singh RECENT BLOGS Double Marker Test October 16, 2024 About Double Marker Test:Imagine embarking on the journey of parenthood with the knowledge that early […] READ MORE Understanding Shingles: Symptoms, Causes, and Prevention October 16, 2024 IntroductionImagine feeling intense pain and burning sensations. Also, imagine a rash that feels like it’s […] READ MORE XRAY at Home October 16, 2024 Bringing Advanced Diagnostic Services to Your Doorstep Lifecare Diagnostics offers in home xray services in […] READ MORE Our Team CEO & DIRECTOR Dr. Vinay Goel DIRECTOR Mrs. Anita Goel MARKETING HEAD Mr. Vishwanath Naik RADIOLOGIST Dr. Smita Dudhal Dr. Hanish Devadiga Dr. Aamir Usman Dr. Sanjay Somane PATHOLOGIST Dr. Vijay Varde Dr. Rohini Siddhant Gedam MICROBIOLOGIST Dr. Pooja Bhalgat CARDIOLOGIST Dr. B D Kate Dr. Hanish Devadiga Dr. Kaveri V Dr. Shilpa Singh GYNECOLOGIST Dr. Veena Shinde Dr. Mrunal Kherde ORTHOPEDIC Dr. J P Jain CHEST PHYSICIAN Dr. Dheeraj Yadav CORPORATE CLIENTS Covid Test Lifecare logo Franchise Gift Voucher Feedback FAQ’S Media Blog Career Contact us NewsLetter Privacy Policy Disclaimer Lifecare Diagnostics & Research Center Pvt. Ltd © 2026",
  "text_truncated": false,
  "extracted_at": "2026-06-16T02:43:47+00:00",
  "facility_id": "18fd7cd5-98f9-42f7-a947-39e978c29cee",
  "facility_name": "Lifecare Diagnostic",
  "http_status": 200
}